leo_packer/__init__.py
leo_packer/_xor.c
leo_packer/_xor.cpython-312-darwin.so
leo_packer/cli.py
leo_packer/compress.py
leo_packer/core.py
leo_packer/errors.py
leo_packer/obfuscate.py
leo_packer/pack_reader.py
leo_packer/util.py
leo_packer-1.0.2.dist-info/licenses/LICENSE
leo_packer-1.0.2.dist-info/METADATA
leo_packer-1.0.2.dist-info/WHEEL
leo_packer-1.0.2.dist-info/entry_points.txt
leo_packer-1.0.2.dist-info/top_level.txt
leo_packer-1.0.2.dist-info/RECORD
