Metadata-Version: 2.4
Name: leo-packer
Version: 1.0.2
Summary: Pack and unpack Leo Pack archives
Author-email: bluesentinelsec <bluesentinel@protonmail.com>
License: GPL-3.0-only
Project-URL: Homepage, https://github.com/bluesentinelsec/leo-packer
Project-URL: Repository, https://github.com/bluesentinelsec/leo-packer.git
Keywords: game,engine,packer,file packer,virtual file system,archive
Classifier: Programming Language :: Python :: 3
Classifier: Programming Language :: Python :: 3.8
Classifier: License :: OSI Approved :: GNU General Public License v3 (GPLv3)
Classifier: Operating System :: OS Independent
Requires-Python: >=3.8
License-File: LICENSE
Provides-Extra: dev
Requires-Dist: pytest>=8.0; extra == "dev"
Dynamic: license-file
